BDPoisson1D/DirichletLinear.cpython-37m-darwin.so
BDPoisson1D/DirichletLinear.pxd
BDPoisson1D/DirichletNonLinear.cpython-37m-darwin.so
BDPoisson1D/DirichletNonLinear.pxd
BDPoisson1D/FirstOrderLinear.cpython-37m-darwin.so
BDPoisson1D/FirstOrderLinear.pxd
BDPoisson1D/FirstOrderNonLinear.cpython-37m-darwin.so
BDPoisson1D/FirstOrderNonLinear.pxd
BDPoisson1D/NeumannLinear.cpython-37m-darwin.so
BDPoisson1D/NeumannLinear.pxd
BDPoisson1D/__init__.py
BDPoisson1D/_helpers.cpython-37m-darwin.so
BDPoisson1D/_helpers.pxd
BDPoisson1D/_version.py
BDPoisson1D-0.3.5.dist-info/LICENSE.txt
BDPoisson1D-0.3.5.dist-info/METADATA
BDPoisson1D-0.3.5.dist-info/NOTICE.txt
BDPoisson1D-0.3.5.dist-info/WHEEL
BDPoisson1D-0.3.5.dist-info/top_level.txt
BDPoisson1D-0.3.5.dist-info/RECORD
