Metadata-Version: 2.1
Name: BDPoisson1D
Version: 0.3.5
Summary: BD Finite Difference Poisson equation solver
Home-page: https://github.com/bond-anton/BDPoisson1D
Author: Anton Bondarenko
Author-email: bond.anton@gmail.com
License: Apache Software License
Keywords: FiniteDifference PDE Poisson
Platform: UNKNOWN
Classifier: Development Status :: 3 - Alpha
Classifier: Intended Audience :: Education
Classifier: Intended Audience :: Science/Research
Classifier: License :: OSI Approved :: Apache Software License
Classifier: Topic :: Scientific/Engineering :: Mathematics
Classifier: Programming Language :: Python :: 3
Classifier: Programming Language :: Python :: 3.6
Classifier: Programming Language :: Python :: 3.7
Classifier: Programming Language :: Python :: 3.8
Classifier: Programming Language :: Python :: 3.9
License-File: LICENSE.txt
License-File: NOTICE.txt
Requires-Dist: numpy
Requires-Dist: scipy (>=0.17.0)
Requires-Dist: matplotlib
Requires-Dist: BDMesh (>=0.2.18)
Requires-Dist: BDFunction1D (>=0.1.2)
